snakesist/__init__.py
snakesist/delb_plugins.py
snakesist/exceptions.py
snakesist/exist_client.py
snakesist-0.3.0.dist-info/entry_points.txt
snakesist-0.3.0.dist-info/LICENSE.txt
snakesist-0.3.0.dist-info/WHEEL
snakesist-0.3.0.dist-info/METADATA
snakesist-0.3.0.dist-info/RECORD
