Metadata-Version: 2.1
Name: snakesist
Version: 0.3.0
Summary: A Python database interface for eXist-db
Home-page: https://github.com/delb-xml/snakesist
License: MIT
Keywords: xml,exist-db,client
Author: Theodor Costea
Author-email: theo.costea@gmail.com
Requires-Python: >=3.7,<4.0
Classifier: Development Status :: 4 - Beta
Classifier: Intended Audience :: Developers
Classifier: Intended Audience :: Science/Research
Classifier: License :: OSI Approved :: MIT License
Classifier: Natural Language :: English
Classifier: Programming Language :: Python :: 3
Classifier: Programming Language :: Python :: 3.10
Classifier: Programming Language :: Python :: 3.7
Classifier: Programming Language :: Python :: 3.8
Classifier: Programming Language :: Python :: 3.9
Classifier: Topic :: Text Processing :: Markup :: XML
Requires-Dist: delb[https-loader] (>=0.4,<0.5)
Requires-Dist: importlib_metadata; python_version < "3.8"
Project-URL: Repository, https://github.com/delb-xml/snakesist
